chunkydl/__init__.py
chunkydl/api.py
chunkydl/core.py
chunkydl/download.py
chunkydl/exceptions.py
chunkydl/models/__init__.py
chunkydl/models/data_models.py
chunkydl/models/download_config.py
chunkydl/models/multi_part_downloader.py
chunkydl/models/queue_downloader.py
chunkydl/models/size.py
chunkydl/runner.py
chunkydl/utils.py
chunkydl-0.2.0.dist-info/LICENSE
chunkydl-0.2.0.dist-info/METADATA
chunkydl-0.2.0.dist-info/WHEEL
chunkydl-0.2.0.dist-info/RECORD
